LICENSE
MANIFEST.in
README.md
setup.py
src/marlight.py
src/marlight.egg-info/PKG-INFO
src/marlight.egg-info/SOURCES.txt
src/marlight.egg-info/dependency_links.txt
src/marlight.egg-info/top_level.txt