Metadata-Version: 1.1
Name: marlight
Version: 0.0.1.post1
Summary: Marglight RGBW control through ethernet bridge
Home-page: UNKNOWN
Author: Nicolas Gilles
Author-email: nicolas.gilles@gmail.com
License: BSD 2-Clause
Platform: UNKNOWN
Classifier: Development Status :: 3 - Alpha
Classifier: Intended Audience :: Developers
Classifier: License :: OSI Approved :: BSD License
Classifier: Operating System :: OS Independent
